wcommon/__init__.py
wcommon/calc.py
wcommon-0.2.1.dist-info/METADATA
wcommon-0.2.1.dist-info/WHEEL
wcommon-0.2.1.dist-info/top_level.txt
wcommon-0.2.1.dist-info/RECORD
